slimgui/__init__.py
slimgui/slimgui_ext.cpython-310-x86_64-linux-gnu.so
slimgui/imgui/__init__.py
slimgui/implot/__init__.py
slimgui/integrations/__init__.py
slimgui/integrations/base.py
slimgui/integrations/glfw.py
slimgui/integrations/null.py
slimgui/integrations/opengl.py
slimgui/slimgui_ext/__init__.pyi
slimgui/slimgui_ext/imgui.pyi
slimgui/slimgui_ext/implot.pyi
slimgui-0.6.0.dist-info/METADATA
slimgui-0.6.0.dist-info/WHEEL
slimgui-0.6.0.dist-info/RECORD
slimgui-0.6.0.dist-info/licenses/LICENSE.txt
