Metadata-Version: 2.1
Name: slimgui
Version: 0.6.0
Summary: Python Dear ImGui bindings
Author-Email: Janne Hellsten <jjhellst@gmail.com>
Classifier: Development Status :: 4 - Beta
Classifier: Intended Audience :: Developers
Classifier: License :: OSI Approved :: MIT License
Project-URL: Documentation, https://nurpax.github.io/slimgui/
Project-URL: Repository, https://github.com/nurpax/slimgui
Requires-Python: >=3.10
